{
  "annotations": {
    "list": [
      {
        "builtIn": 1,
        "datasource": {
          "type": "grafana",
          "uid": "-- Grafana --"
        },
        "enable": true,
        "hide": true,
        "iconColor": "rgba(0, 211, 255, 1)",
        "name": "Annotations & Alerts",
        "target": {
          "limit": 100,
          "matchAny": false,
          "tags": [],
          "type": "dashboard"
        },
        "type": "dashboard"
      }
    ]
  },
  "editable": true,
  "fiscalYearStartMonth": 0,
  "graphTooltip": 0,
  "links": [],
  "liveNow": false,
  "panels": [
    {
      "collapsed": false,
      "gridPos": {
        "h": 1,
        "w": 24,
        "x": 0,
        "y": 0
      },
      "id": 4,
      "panels": [],
      "title": "Counters",
      "type": "row"
    },
    {
      "datasource": {
        "type": "loki",
        "uid": "P8E80F9AEF21F6940"
      },
      "fieldConfig": {
        "defaults": {
          "color": {
            "fixedColor": "red",
            "mode": "shades"
          },
          "mappings": [],
          "noValue": "0",
          "thresholds": {
            "mode": "absolute",
            "steps": [
              {
                "color": "green",
                "value": null
              }
            ]
          },
          "unit": "none"
        },
        "overrides": []
      },
      "gridPos": {
        "h": 6,
        "w": 4,
        "x": 0,
        "y": 1
      },
      "id": 5,
      "options": {
        "colorMode": "value",
        "graphMode": "none",
        "justifyMode": "center",
        "orientation": "vertical",
        "reduceOptions": {
          "calcs": [
            "lastNotNull"
          ],
          "fields": "",
          "values": false
        },
        "textMode": "auto"
      },
      "pluginVersion": "10.1.4",
      "targets": [
        {
          "datasource": {
            "type": "loki",
            "uid": "P8E80F9AEF21F6940"
          },
          "editorMode": "builder",
          "expr": "count_over_time({level=\"ERROR\", service_name=\"$service_name\"} [$__range])",
          "queryType": "range",
          "refId": "A"
        }
      ],
      "title": "ERROR Count",
      "transparent": true,
      "type": "stat"
    },
    {
      "datasource": {
        "type": "loki",
        "uid": "P8E80F9AEF21F6940"
      },
      "fieldConfig": {
        "defaults": {
          "color": {
            "fixedColor": "green",
            "mode": "shades"
          },
          "mappings": [],
          "noValue": "0",
          "thresholds": {
            "mode": "absolute",
            "steps": [
              {
                "color": "green",
                "value": null
              }
            ]
          },
          "unit": "none"
        },
        "overrides": []
      },
      "gridPos": {
        "h": 6,
        "w": 4,
        "x": 4,
        "y": 1
      },
      "id": 6,
      "options": {
        "colorMode": "value",
        "graphMode": "none",
        "justifyMode": "center",
        "orientation": "vertical",
        "reduceOptions": {
          "calcs": [
            "lastNotNull"
          ],
          "fields": "",
          "values": false
        },
        "textMode": "auto"
      },
      "pluginVersion": "10.1.4",
      "targets": [
        {
          "datasource": {
            "type": "loki",
            "uid": "P8E80F9AEF21F6940"
          },
          "editorMode": "builder",
          "expr": "count_over_time({level=\"INFO\", service_name=\"$service_name\"} [$__range])",
          "queryType": "range",
          "refId": "A"
        }
      ],
      "title": "INFO Count",
      "transparent": true,
      "type": "stat"
    },
    {
      "datasource": {
        "type": "loki",
        "uid": "P8E80F9AEF21F6940"
      },
      "fieldConfig": {
        "defaults": {
          "color": {
            "fixedColor": "orange",
            "mode": "shades"
          },
          "mappings": [],
          "noValue": "0",
          "thresholds": {
            "mode": "absolute",
            "steps": [
              {
                "color": "green",
                "value": null
              }
            ]
          },
          "unit": "none"
        },
        "overrides": []
      },
      "gridPos": {
        "h": 6,
        "w": 4,
        "x": 8,
        "y": 1
      },
      "id": 7,
      "options": {
        "colorMode": "value",
        "graphMode": "none",
        "justifyMode": "center",
        "orientation": "vertical",
        "reduceOptions": {
          "calcs": [
            "lastNotNull"
          ],
          "fields": "",
          "values": false
        },
        "textMode": "auto"
      },
      "pluginVersion": "10.1.4",
      "targets": [
        {
          "datasource": {
            "type": "loki",
            "uid": "P8E80F9AEF21F6940"
          },
          "editorMode": "builder",
          "expr": "count_over_time({level=\"WARN\", service_name=\"$service_name\"} [$__range])",
          "queryType": "range",
          "refId": "A"
        }
      ],
      "title": "WARN Count",
      "transparent": true,
      "type": "stat"
    },
    {
      "collapsed": false,
      "gridPos": {
        "h": 1,
        "w": 24,
        "x": 0,
        "y": 7
      },
      "id": 3,
      "panels": [],
      "title": "Logs",
      "type": "row"
    },
    {
      "datasource": {
        "type": "loki",
        "uid": "P8E80F9AEF21F6940"
      },
      "gridPos": {
        "h": 33,
        "w": 24,
        "x": 0,
        "y": 8
      },
      "id": 2,
      "options": {
        "dedupStrategy": "none",
        "enableLogDetails": true,
        "prettifyLogMessage": false,
        "showCommonLabels": false,
        "showLabels": false,
        "showTime": true,
        "sortOrder": "Descending",
        "wrapLogMessage": false
      },
      "pluginVersion": "9.3.2",
      "targets": [
        {
          "datasource": {
            "type": "loki",
            "uid": "P8E80F9AEF21F6940"
          },
          "editorMode": "builder",
          "expr": "{service_name=\"$service_name\"} | json | level =~ `$level` | line_format `[{{ .level }}] {{ .body }}`",
          "queryType": "range",
          "refId": "A"
        }
      ],
      "title": "Logs",
      "type": "logs"
    }
  ],
  "refresh": "1m",
  "schemaVersion": 38,
  "style": "dark",
  "tags": [],
  "templating": {
    "list": [
      {
        "current": {
          "selected": true,
          "text": "OrderManagement",
          "value": "OrderManagement"
        },
        "datasource": {
          "type": "loki",
          "uid": "P8E80F9AEF21F6940"
        },
        "definition": "",
        "hide": 0,
        "includeAll": false,
        "label": "Service",
        "multi": false,
        "name": "service_name",
        "options": [],
        "query": {
          "label": "service_name",
          "refId": "LokiVariableQueryEditor-VariableQuery",
          "stream": "",
          "type": 1
        },
        "refresh": 1,
        "regex": "",
        "skipUrlSync": false,
        "sort": 1,
        "type": "query"
      },
      {
        "current": {
          "selected": true,
          "text": "All",
          "value": "$__all"
        },
        "datasource": {
          "type": "loki",
          "uid": "P8E80F9AEF21F6940"
        },
        "definition": "",
        "hide": 0,
        "includeAll": true,
        "label": "Level",
        "multi": false,
        "name": "level",
        "options": [],
        "query": {
          "label": "level",
          "refId": "LokiVariableQueryEditor-VariableQuery",
          "stream": "",
          "type": 1
        },
        "refresh": 1,
        "regex": "",
        "skipUrlSync": false,
        "sort": 0,
        "type": "query"
      }
    ]
  },
  "time": {
    "from": "now-1h",
    "to": "now"
  },
  "timepicker": {},
  "timezone": "",
  "title": "Logs",
  "uid": "g4tAIpp4z",
  "version": 1,
  "weekStart": ""
}